datacls/__init__.py
datacls-4.8.0.dist-info/LICENSE
datacls-4.8.0.dist-info/METADATA
datacls-4.8.0.dist-info/WHEEL
datacls-4.8.0.dist-info/RECORD
