Metadata-Version: 2.1
Name: datacls
Version: 4.8.0
Summary: 🗂 Take the edge off `dataclass` 🗂
Home-page: https://github.com/rec/datacls
Author: Tom Ritchford
Author-email: tom@swirly.com
Requires-Python: >=3.8
Classifier: Programming Language :: Python :: 3
Classifier: Programming Language :: Python :: 3.8
Classifier: Programming Language :: Python :: 3.9
Classifier: Programming Language :: Python :: 3.10
Classifier: Programming Language :: Python :: 3.11
Classifier: Programming Language :: Python :: 3.12
Requires-Dist: dtyper (>=2.5.0)
Requires-Dist: xmod
Project-URL: Documentation, https://rec.github.io/datacls
Project-URL: Repository, https://github.com/rec/datacls
